{"SIMPLE":["T","file does conform to FITS standard"],"BITPIX":["-32","number of bits per data pixel"],"NAXIS":["3","number of data axes"],"NAXIS1":["2160","length of data axis 1"],"NAXIS2":["3840","length of data axis 2"],"NAXIS3":["3","length of data axis 3"],"EXTEND":["T","FITS dataset may contain extensions"],"COMMENT":"and Astrophysics', volume 376, page 359; bibcode: 2001A&A...376..359H","BZERO":["0.","offset data range to that of unsigned short"],"BSCALE":["1.","default scaling factor"],"INSTRUME":["'Seestar S50'","instrument name"],"TELESCOP":["'Seestar S50'","telescope used to acquire this image"],"DATE":["'2024-02-04T13:38:40'","UTC date that FITS file was created"],"DATE-OBS":["'2024-02-03T23:29:46.267487'","YYYY-MM-DDThh:mm:ss observation start,"],"STACKCNT":["133","Stack frames"],"EXPTIME":["20.","Exposure time [s]"],"LIVETIME":["2660.","Exposure time after deadtime correction"],"EXPSTART":["2460344.47900772","Exposure start time (standard Julian date)"],"EXPEND":["2460344.53086748","Exposure end time (standard Julian date)"],"XPIXSZ":["1.45","X pixel size microns"],"YPIXSZ":["1.45","Y pixel size microns"],"XBINNING":["1","Camera binning mode"],"YBINNING":["1","Camera binning mode"],"FOCALLEN":["250.","Camera focal length"],"CCD-TEMP":["23.75","CCD temp in C"],"FILTER":["'LP      '","Active filter name"],"IMAGETYP":["'Light   '","Type of image"],"OBJECT":["'NGC 1579'","Name of the object of interest"],"GAIN":["80","Camera gain"],"PROGRAM":["'Siril v1.2.1'","Software that created this HDU"],"RA":["67.95417","Image center Right Ascension (deg)"],"DEC":["35.321389","Image center Declination (deg)"],"HISTORY":"hting, unequalized RGB","width":2065,"height":3304}